{"id": "2496", "name": "卓越", "price": 63.4, "change": -1.1, "changePct": -1.71, "volume": 25, "turnover": 0.02, "marketCap": 12, "shares": 0.19, "instNet": -2, "instStreak": 0, "foreignPct": 23.22, "score": 46, "roe": null, "per": 9.91, "pbr": 1.41, "yieldPct": 7.89, "rating": {"level": 0, "label": "強力偏空", "cls": "r-sd"}, "ratingLevel": 0, "fired": false, "sig": {"fired": false, "instBacked": false, "signalIndex": 34, "conditions": [{"key": "c1", "label": "量價突破：單日漲幅 > 4%", "pass": false}, {"key": "c2", "label": "創近 15 日收盤新高", "pass": false}, {"key": "c3", "label": "帶量上攻：量 > 前5日均量 ×1.5", "pass": true}, {"key": "c4", "label": "動能濾網：近 20 日報酬為正", "pass": false}, {"key": "c5a", "label": "型態：前三日收盤連續遞減", "pass": false}, {"key": "c5b", "label": "型態：第2、3日收黑（2 黑）", "pass": false}, {"key": "c5c", "label": "型態：第4日翻紅突破（1 紅）", "pass": false}]}, "kline": [{"time": "2026-05-08", "open": 65.2, "high": 66.2, "low": 65.2, "close": 65.9, "volume": 44}, {"time": "2026-05-11", "open": 65.9, "high": 66.3, "low": 65.9, "close": 66.2, "volume": 31}, {"time": "2026-05-12", "open": 65.5, "high": 66.3, "low": 65.3, "close": 65.9, "volume": 35}, {"time": "2026-05-13", "open": 65.1, "high": 65.6, "low": 64.9, "close": 65.0, "volume": 37}, {"time": "2026-05-14", "open": 65.0, "high": 65.2, "low": 64.7, "close": 64.7, "volume": 42}, {"time": "2026-05-15", "open": 65.2, "high": 65.2, "low": 64.7, "close": 64.8, "volume": 20}, {"time": "2026-05-18", "open": 64.8, "high": 64.8, "low": 64.3, "close": 64.8, "volume": 9}, {"time": "2026-05-19", "open": 64.8, "high": 64.8, "low": 64.5, "close": 64.5, "volume": 21}, {"time": "2026-05-20", "open": 64.8, "high": 64.8, "low": 64.2, "close": 64.3, "volume": 12}, {"time": "2026-05-21", "open": 64.7, "high": 64.7, "low": 64.2, "close": 64.5, "volume": 13}, {"time": "2026-05-22", "open": 64.2, "high": 64.7, "low": 64.2, "close": 64.5, "volume": 12}, {"time": "2026-05-25", "open": 64.8, "high": 64.8, "low": 64.2, "close": 64.5, "volume": 19}, {"time": "2026-05-26", "open": 65.4, "high": 65.4, "low": 64.5, "close": 64.8, "volume": 8}, {"time": "2026-05-27", "open": 65.2, "high": 65.2, "low": 64.3, "close": 65.0, "volume": 23}, {"time": "2026-05-28", "open": 65.3, "high": 65.3, "low": 64.6, "close": 64.7, "volume": 16}, {"time": "2026-05-29", "open": 64.7, "high": 65.0, "low": 64.6, "close": 64.8, "volume": 11}, {"time": "2026-06-01", "open": 64.8, "high": 64.8, "low": 64.5, "close": 64.7, "volume": 15}, {"time": "2026-06-02", "open": 64.7, "high": 65.0, "low": 64.5, "close": 64.6, "volume": 35}, {"time": "2026-06-03", "open": 64.9, "high": 65.0, "low": 64.5, "close": 65.0, "volume": 32}, {"time": "2026-06-04", "open": 65.0, "high": 65.9, "low": 64.9, "close": 65.9, "volume": 35}, {"time": "2026-06-05", "open": 65.3, "high": 66.2, "low": 65.0, "close": 65.3, "volume": 31}, {"time": "2026-06-08", "open": 64.4, "high": 65.4, "low": 64.3, "close": 64.5, "volume": 21}, {"time": "2026-06-09", "open": 64.6, "high": 65.1, "low": 64.6, "close": 64.7, "volume": 23}, {"time": "2026-06-10", "open": 65.6, "high": 65.6, "low": 64.4, "close": 64.5, "volume": 17}, {"time": "2026-06-11", "open": 64.8, "high": 64.8, "low": 64.3, "close": 64.7, "volume": 9}, {"time": "2026-06-12", "open": 64.4, "high": 64.9, "low": 64.4, "close": 64.9, "volume": 8}, {"time": "2026-06-15", "open": 66.3, "high": 66.3, "low": 64.7, "close": 64.9, "volume": 16}, {"time": "2026-06-16", "open": 64.7, "high": 65.0, "low": 64.6, "close": 65.0, "volume": 6}, {"time": "2026-06-17", "open": 65.0, "high": 65.0, "low": 64.1, "close": 64.5, "volume": 17}, {"time": "2026-06-18", "open": 64.9, "high": 65.1, "low": 64.8, "close": 65.0, "volume": 19}, {"time": "2026-06-22", "open": 65.2, "high": 65.9, "low": 65.1, "close": 65.1, "volume": 9}, {"time": "2026-06-23", "open": 65.8, "high": 65.8, "low": 64.9, "close": 65.3, "volume": 11}, {"time": "2026-06-24", "open": 63.7, "high": 65.3, "low": 63.6, "close": 64.5, "volume": 24}, {"time": "2026-06-25", "open": 64.5, "high": 65.0, "low": 64.5, "close": 64.5, "volume": 14}, {"time": "2026-06-26", "open": 64.2, "high": 64.2, "low": 63.4, "close": 63.4, "volume": 25}], "instBars": [{"time": "2026-05-14", "value": -2}, {"time": "2026-05-15", "value": -4}, {"time": "2026-05-18", "value": -2}, {"time": "2026-05-19", "value": -4}, {"time": "2026-05-20", "value": -2}, {"time": "2026-05-21", "value": -2}, {"time": "2026-05-22", "value": 3}, {"time": "2026-05-25", "value": 3}, {"time": "2026-05-26", "value": 1}, {"time": "2026-05-27", "value": -1}, {"time": "2026-05-28", "value": -2}, {"time": "2026-05-29", "value": 2}, {"time": "2026-06-01", "value": 1}, {"time": "2026-06-02", "value": 0}, {"time": "2026-06-03", "value": 4}, {"time": "2026-06-04", "value": 6}, {"time": "2026-06-05", "value": 0}, {"time": "2026-06-08", "value": -2}, {"time": "2026-06-09", "value": -3}, {"time": "2026-06-10", "value": -8}, {"time": "2026-06-11", "value": -3}, {"time": "2026-06-12", "value": -5}, {"time": "2026-06-16", "value": 2}, {"time": "2026-06-17", "value": -1}, {"time": "2026-06-18", "value": 0}, {"time": "2026-06-22", "value": 0}, {"time": "2026-06-23", "value": -1}, {"time": "2026-06-24", "value": 0}, {"time": "2026-06-25", "value": -1}, {"time": "2026-06-26", "value": -2}], "foreignTrend": [{"time": "2026-05-14", "value": 23.19}, {"time": "2026-05-15", "value": 23.16}, {"time": "2026-05-18", "value": 23.15}, {"time": "2026-05-19", "value": 23.13}, {"time": "2026-05-20", "value": 23.12}, {"time": "2026-05-21", "value": 23.12}, {"time": "2026-05-22", "value": 23.13}, {"time": "2026-05-25", "value": 23.15}, {"time": "2026-05-26", "value": 23.26}, {"time": "2026-05-27", "value": 23.25}, {"time": "2026-05-28", "value": 23.24}, {"time": "2026-05-29", "value": 23.25}, {"time": "2026-06-01", "value": 23.26}, {"time": "2026-06-02", "value": 23.26}, {"time": "2026-06-03", "value": 23.28}, {"time": "2026-06-04", "value": 23.31}, {"time": "2026-06-05", "value": 23.31}, {"time": "2026-06-08", "value": 23.31}, {"time": "2026-06-09", "value": 23.3}, {"time": "2026-06-10", "value": 23.27}, {"time": "2026-06-11", "value": 23.26}, {"time": "2026-06-12", "value": 23.23}, {"time": "2026-06-15", "value": 23.23}, {"time": "2026-06-16", "value": 23.24}, {"time": "2026-06-17", "value": 23.24}, {"time": "2026-06-18", "value": 23.24}, {"time": "2026-06-22", "value": 23.23}, {"time": "2026-06-23", "value": 23.23}, {"time": "2026-06-24", "value": 23.23}, {"time": "2026-06-25", "value": 23.22}], "sparkCloses": [64.5, 64.5, 64.8, 65.0, 64.7, 64.8, 64.7, 64.6, 65.0, 65.9, 65.3, 64.5, 64.7, 64.5, 64.7, 64.9, 64.9, 65.0, 64.5, 65.0, 65.1, 65.3, 64.5, 64.5, 63.4]}