{"id": "4743", "name": "合一", "price": 48.15, "change": -2.05, "changePct": -4.08, "volume": 3037, "turnover": 1.46, "marketCap": 231, "shares": 4.8, "instNet": -983, "instStreak": 0, "foreignPct": 8.21, "score": 35, "roe": null, "per": 0.0, "pbr": 2.3, "yieldPct": 0.0, "rating": {"level": 0, "label": "強力偏空", "cls": "r-sd"}, "ratingLevel": 0, "fired": false, "sig": {"fired": false, "instBacked": false, "signalIndex": 34, "conditions": [{"key": "c1", "label": "量價突破：單日漲幅 > 4%", "pass": false}, {"key": "c2", "label": "創近 15 日收盤新高", "pass": false}, {"key": "c3", "label": "帶量上攻：量 > 前5日均量 ×1.5", "pass": true}, {"key": "c4", "label": "動能濾網：近 20 日報酬為正", "pass": false}, {"key": "c5a", "label": "型態：前三日收盤連續遞減", "pass": false}, {"key": "c5b", "label": "型態：第2、3日收黑（2 黑）", "pass": false}, {"key": "c5c", "label": "型態：第4日翻紅突破（1 紅）", "pass": false}]}, "kline": [{"time": "2026-05-08", "open": 53.3, "high": 53.7, "low": 51.5, "close": 51.6, "volume": 2113}, {"time": "2026-05-11", "open": 52.8, "high": 53.1, "low": 51.1, "close": 51.5, "volume": 2373}, {"time": "2026-05-12", "open": 51.7, "high": 51.7, "low": 50.4, "close": 51.0, "volume": 2049}, {"time": "2026-05-13", "open": 51.0, "high": 52.2, "low": 50.7, "close": 50.7, "volume": 2072}, {"time": "2026-05-14", "open": 50.8, "high": 52.3, "low": 50.4, "close": 52.0, "volume": 2409}, {"time": "2026-05-15", "open": 52.3, "high": 52.3, "low": 50.2, "close": 50.3, "volume": 2550}, {"time": "2026-05-18", "open": 50.6, "high": 50.8, "low": 49.8, "close": 50.3, "volume": 1629}, {"time": "2026-05-19", "open": 50.4, "high": 51.8, "low": 50.0, "close": 50.0, "volume": 1456}, {"time": "2026-05-20", "open": 50.4, "high": 51.0, "low": 49.0, "close": 49.0, "volume": 2492}, {"time": "2026-05-21", "open": 53.0, "high": 53.9, "low": 53.0, "close": 53.9, "volume": 2688}, {"time": "2026-05-22", "open": 53.0, "high": 55.2, "low": 51.9, "close": 53.0, "volume": 9730}, {"time": "2026-05-25", "open": 53.7, "high": 53.7, "low": 51.3, "close": 52.0, "volume": 3482}, {"time": "2026-05-26", "open": 52.2, "high": 52.3, "low": 50.4, "close": 50.7, "volume": 2773}, {"time": "2026-05-27", "open": 50.7, "high": 51.1, "low": 50.1, "close": 50.8, "volume": 2392}, {"time": "2026-05-28", "open": 50.8, "high": 50.9, "low": 49.7, "close": 49.7, "volume": 2846}, {"time": "2026-05-29", "open": 50.4, "high": 50.9, "low": 50.0, "close": 50.4, "volume": 2202}, {"time": "2026-06-01", "open": 50.7, "high": 51.9, "low": 49.85, "close": 51.1, "volume": 2828}, {"time": "2026-06-02", "open": 51.2, "high": 51.5, "low": 50.4, "close": 51.2, "volume": 1722}, {"time": "2026-06-03", "open": 50.1, "high": 50.4, "low": 49.1, "close": 50.1, "volume": 3983}, {"time": "2026-06-04", "open": 50.2, "high": 51.6, "low": 49.8, "close": 50.2, "volume": 2339}, {"time": "2026-06-05", "open": 50.7, "high": 51.3, "low": 49.95, "close": 50.4, "volume": 1578}, {"time": "2026-06-08", "open": 48.65, "high": 51.0, "low": 47.35, "close": 49.65, "volume": 2735}, {"time": "2026-06-09", "open": 49.9, "high": 51.0, "low": 49.5, "close": 49.8, "volume": 2166}, {"time": "2026-06-10", "open": 49.8, "high": 50.5, "low": 49.0, "close": 49.0, "volume": 1712}, {"time": "2026-06-11", "open": 49.05, "high": 49.25, "low": 47.5, "close": 47.75, "volume": 2298}, {"time": "2026-06-12", "open": 48.0, "high": 48.8, "low": 47.95, "close": 48.35, "volume": 1357}, {"time": "2026-06-15", "open": 49.0, "high": 49.65, "low": 48.55, "close": 49.15, "volume": 1279}, {"time": "2026-06-16", "open": 49.3, "high": 49.55, "low": 47.85, "close": 47.85, "volume": 1676}, {"time": "2026-06-17", "open": 48.0, "high": 48.1, "low": 47.3, "close": 47.55, "volume": 1505}, {"time": "2026-06-18", "open": 47.85, "high": 48.55, "low": 47.5, "close": 48.0, "volume": 1452}, {"time": "2026-06-22", "open": 48.2, "high": 48.2, "low": 47.8, "close": 47.9, "volume": 1604}, {"time": "2026-06-23", "open": 48.05, "high": 49.35, "low": 48.05, "close": 48.6, "volume": 2165}, {"time": "2026-06-24", "open": 48.4, "high": 49.6, "low": 48.3, "close": 49.4, "volume": 1630}, {"time": "2026-06-25", "open": 50.0, "high": 51.8, "low": 49.7, "close": 50.2, "volume": 2941}, {"time": "2026-06-26", "open": 50.3, "high": 51.2, "low": 48.1, "close": 48.15, "volume": 3037}], "instBars": [{"time": "2026-05-15", "value": -1163}, {"time": "2026-05-18", "value": -403}, {"time": "2026-05-19", "value": -117}, {"time": "2026-05-20", "value": -1024}, {"time": "2026-05-21", "value": -153}, {"time": "2026-05-22", "value": 219}, {"time": "2026-05-25", "value": -787}, {"time": "2026-05-26", "value": -745}, {"time": "2026-05-27", "value": 153}, {"time": "2026-05-28", "value": -1171}, {"time": "2026-05-29", "value": 354}, {"time": "2026-06-01", "value": 317}, {"time": "2026-06-02", "value": 189}, {"time": "2026-06-03", "value": -761}, {"time": "2026-06-04", "value": 227}, {"time": "2026-06-05", "value": 125}, {"time": "2026-06-08", "value": -8}, {"time": "2026-06-09", "value": -390}, {"time": "2026-06-10", "value": -251}, {"time": "2026-06-11", "value": -475}, {"time": "2026-06-12", "value": 356}, {"time": "2026-06-15", "value": 145}, {"time": "2026-06-16", "value": -821}, {"time": "2026-06-17", "value": -24}, {"time": "2026-06-18", "value": 228}, {"time": "2026-06-22", "value": 141}, {"time": "2026-06-23", "value": 544}, {"time": "2026-06-24", "value": 541}, {"time": "2026-06-25", "value": 297}, {"time": "2026-06-26", "value": -983}], "foreignTrend": [{"time": "2026-05-14", "value": 13.7}, {"time": "2026-05-15", "value": 13.57}, {"time": "2026-05-18", "value": 7.27}, {"time": "2026-05-19", "value": 7.31}, {"time": "2026-05-20", "value": 7.2}, {"time": "2026-05-21", "value": 7.24}, {"time": "2026-05-22", "value": 7.38}, {"time": "2026-05-25", "value": 7.27}, {"time": "2026-05-26", "value": 7.19}, {"time": "2026-05-27", "value": 7.26}, {"time": "2026-05-28", "value": 7.12}, {"time": "2026-05-29", "value": 7.26}, {"time": "2026-06-01", "value": 7.38}, {"time": "2026-06-02", "value": 7.5}, {"time": "2026-06-03", "value": 7.49}, {"time": "2026-06-04", "value": 7.57}, {"time": "2026-06-05", "value": 7.64}, {"time": "2026-06-08", "value": 7.69}, {"time": "2026-06-09", "value": 7.66}, {"time": "2026-06-10", "value": 7.67}, {"time": "2026-06-11", "value": 7.68}, {"time": "2026-06-12", "value": 7.77}, {"time": "2026-06-15", "value": 7.81}, {"time": "2026-06-16", "value": 7.73}, {"time": "2026-06-17", "value": 7.77}, {"time": "2026-06-18", "value": 7.83}, {"time": "2026-06-22", "value": 7.87}, {"time": "2026-06-23", "value": 7.99}, {"time": "2026-06-24", "value": 8.11}, {"time": "2026-06-25", "value": 8.21}], "sparkCloses": [53.0, 52.0, 50.7, 50.8, 49.7, 50.4, 51.1, 51.2, 50.1, 50.2, 50.4, 49.65, 49.8, 49.0, 47.75, 48.35, 49.15, 47.85, 47.55, 48.0, 47.9, 48.6, 49.4, 50.2, 48.15]}