{"id": "6708", "name": "天擎", "price": 40.6, "change": 0.6, "changePct": 1.5, "volume": 73, "turnover": 0.03, "marketCap": 12, "shares": 0.29, "instNet": 6, "instStreak": 1, "foreignPct": 3.21, "score": 56, "roe": null, "per": 0.0, "pbr": 3.11, "yieldPct": 0.0, "rating": {"level": 3, "label": "偏多", "cls": "r-u"}, "ratingLevel": 3, "fired": false, "sig": {"fired": false, "instBacked": true, "signalIndex": 34, "conditions": [{"key": "c1", "label": "量價突破：單日漲幅 > 4%", "pass": false}, {"key": "c2", "label": "創近 15 日收盤新高", "pass": false}, {"key": "c3", "label": "帶量上攻：量 > 前5日均量 ×1.5", "pass": true}, {"key": "c4", "label": "動能濾網：近 20 日報酬為正", "pass": false}, {"key": "c5a", "label": "型態：前三日收盤連續遞減", "pass": false}, {"key": "c5b", "label": "型態：第2、3日收黑（2 黑）", "pass": true}, {"key": "c5c", "label": "型態：第4日翻紅突破（1 紅）", "pass": true}]}, "kline": [{"time": "2026-05-08", "open": 42.4, "high": 42.5, "low": 41.4, "close": 41.4, "volume": 33}, {"time": "2026-05-11", "open": 41.95, "high": 43.3, "low": 41.95, "close": 42.8, "volume": 54}, {"time": "2026-05-12", "open": 41.5, "high": 42.9, "low": 41.1, "close": 41.7, "volume": 47}, {"time": "2026-05-13", "open": 42.35, "high": 42.35, "low": 40.3, "close": 40.35, "volume": 36}, {"time": "2026-05-14", "open": 42.8, "high": 42.8, "low": 41.45, "close": 42.45, "volume": 23}, {"time": "2026-05-15", "open": 43.05, "high": 43.05, "low": 41.0, "close": 42.35, "volume": 55}, {"time": "2026-05-18", "open": 42.95, "high": 42.95, "low": 41.0, "close": 41.1, "volume": 33}, {"time": "2026-05-19", "open": 40.75, "high": 40.75, "low": 39.85, "close": 40.0, "volume": 47}, {"time": "2026-05-20", "open": 40.0, "high": 41.0, "low": 39.6, "close": 40.5, "volume": 28}, {"time": "2026-05-21", "open": 40.5, "high": 40.5, "low": 39.5, "close": 40.3, "volume": 52}, {"time": "2026-05-22", "open": 39.05, "high": 40.0, "low": 39.05, "close": 40.0, "volume": 37}, {"time": "2026-05-25", "open": 40.6, "high": 41.8, "low": 40.4, "close": 40.7, "volume": 72}, {"time": "2026-05-26", "open": 40.95, "high": 40.95, "low": 40.5, "close": 40.5, "volume": 26}, {"time": "2026-05-27", "open": 42.25, "high": 42.25, "low": 40.6, "close": 40.6, "volume": 50}, {"time": "2026-05-28", "open": 41.5, "high": 42.5, "low": 40.8, "close": 40.8, "volume": 67}, {"time": "2026-05-29", "open": 40.85, "high": 41.6, "low": 40.0, "close": 41.0, "volume": 78}, {"time": "2026-06-01", "open": 43.45, "high": 43.45, "low": 40.9, "close": 41.1, "volume": 66}, {"time": "2026-06-02", "open": 41.0, "high": 41.15, "low": 40.25, "close": 40.85, "volume": 48}, {"time": "2026-06-03", "open": 41.65, "high": 41.65, "low": 40.0, "close": 40.3, "volume": 92}, {"time": "2026-06-04", "open": 40.0, "high": 40.35, "low": 39.95, "close": 40.35, "volume": 18}, {"time": "2026-06-05", "open": 40.85, "high": 42.5, "low": 40.55, "close": 41.5, "volume": 73}, {"time": "2026-06-08", "open": 38.5, "high": 40.45, "low": 38.5, "close": 39.5, "volume": 113}, {"time": "2026-06-09", "open": 39.5, "high": 40.5, "low": 39.5, "close": 39.7, "volume": 36}, {"time": "2026-06-10", "open": 39.2, "high": 39.65, "low": 38.75, "close": 38.75, "volume": 47}, {"time": "2026-06-11", "open": 40.5, "high": 40.5, "low": 38.65, "close": 38.75, "volume": 15}, {"time": "2026-06-12", "open": 39.5, "high": 39.5, "low": 39.05, "close": 39.2, "volume": 11}, {"time": "2026-06-15", "open": 39.75, "high": 39.75, "low": 39.05, "close": 39.3, "volume": 20}, {"time": "2026-06-16", "open": 39.3, "high": 39.5, "low": 39.0, "close": 39.2, "volume": 18}, {"time": "2026-06-17", "open": 38.65, "high": 39.25, "low": 38.0, "close": 39.2, "volume": 29}, {"time": "2026-06-18", "open": 39.45, "high": 40.5, "low": 39.45, "close": 39.8, "volume": 24}, {"time": "2026-06-22", "open": 40.5, "high": 40.8, "low": 39.7, "close": 40.55, "volume": 60}, {"time": "2026-06-23", "open": 40.8, "high": 40.8, "low": 40.2, "close": 40.35, "volume": 55}, {"time": "2026-06-24", "open": 40.35, "high": 40.35, "low": 39.8, "close": 40.0, "volume": 10}, {"time": "2026-06-25", "open": 40.6, "high": 40.6, "low": 39.3, "close": 40.0, "volume": 18}, {"time": "2026-06-26", "open": 39.95, "high": 41.9, "low": 39.9, "close": 40.6, "volume": 73}], "instBars": [{"time": "2026-05-13", "value": -1}, {"time": "2026-05-14", "value": -1}, {"time": "2026-05-15", "value": 2}, {"time": "2026-05-18", "value": 0}, {"time": "2026-05-20", "value": 1}, {"time": "2026-05-21", "value": -1}, {"time": "2026-05-25", "value": 1}, {"time": "2026-05-26", "value": -2}, {"time": "2026-05-27", "value": 0}, {"time": "2026-05-28", "value": 3}, {"time": "2026-05-29", "value": -1}, {"time": "2026-06-01", "value": 1}, {"time": "2026-06-02", "value": -1}, {"time": "2026-06-03", "value": 3}, {"time": "2026-06-04", "value": 0}, {"time": "2026-06-05", "value": 0}, {"time": "2026-06-08", "value": -4}, {"time": "2026-06-09", "value": -4}, {"time": "2026-06-10", "value": -1}, {"time": "2026-06-11", "value": -6}, {"time": "2026-06-12", "value": -1}, {"time": "2026-06-15", "value": -11}, {"time": "2026-06-16", "value": 1}, {"time": "2026-06-17", "value": 1}, {"time": "2026-06-18", "value": 1}, {"time": "2026-06-22", "value": 9}, {"time": "2026-06-23", "value": -6}, {"time": "2026-06-24", "value": -1}, {"time": "2026-06-25", "value": -2}, {"time": "2026-06-26", "value": 6}], "foreignTrend": [{"time": "2026-05-14", "value": 3.14}, {"time": "2026-05-15", "value": 3.15}, {"time": "2026-05-18", "value": 3.15}, {"time": "2026-05-19", "value": 3.15}, {"time": "2026-05-20", "value": 3.15}, {"time": "2026-05-21", "value": 3.15}, {"time": "2026-05-22", "value": 3.15}, {"time": "2026-05-25", "value": 3.15}, {"time": "2026-05-26", "value": 3.14}, {"time": "2026-05-27", "value": 3.14}, {"time": "2026-05-28", "value": 3.15}, {"time": "2026-05-29", "value": 3.15}, {"time": "2026-06-01", "value": 3.16}, {"time": "2026-06-02", "value": 3.16}, {"time": "2026-06-03", "value": 3.17}, {"time": "2026-06-04", "value": 3.17}, {"time": "2026-06-05", "value": 3.17}, {"time": "2026-06-08", "value": 3.15}, {"time": "2026-06-09", "value": 3.14}, {"time": "2026-06-10", "value": 3.24}, {"time": "2026-06-11", "value": 3.22}, {"time": "2026-06-12", "value": 3.22}, {"time": "2026-06-15", "value": 3.19}, {"time": "2026-06-16", "value": 3.19}, {"time": "2026-06-17", "value": 3.2}, {"time": "2026-06-18", "value": 3.21}, {"time": "2026-06-22", "value": 3.24}, {"time": "2026-06-23", "value": 3.22}, {"time": "2026-06-24", "value": 3.21}, {"time": "2026-06-25", "value": 3.21}], "sparkCloses": [40.0, 40.7, 40.5, 40.6, 40.8, 41.0, 41.1, 40.85, 40.3, 40.35, 41.5, 39.5, 39.7, 38.75, 38.75, 39.2, 39.3, 39.2, 39.2, 39.8, 40.55, 40.35, 40.0, 40.0, 40.6]}