{"id": "6787", "name": "晶瑞光", "price": 33.65, "change": -2.8, "changePct": -7.68, "volume": 1569, "turnover": 0.53, "marketCap": 0, "shares": 0, "instNet": -77, "instStreak": 0, "foreignPct": 0.0, "score": 63, "roe": null, "per": null, "pbr": null, "yieldPct": null, "rating": {"level": 3, "label": "偏多", "cls": "r-u"}, "ratingLevel": 3, "fired": false, "sig": {"fired": false, "instBacked": false, "signalIndex": 34, "conditions": [{"key": "c1", "label": "量價突破：單日漲幅 > 4%", "pass": false}, {"key": "c2", "label": "創近 15 日收盤新高", "pass": false}, {"key": "c3", "label": "帶量上攻：量 > 前5日均量 ×1.5", "pass": true}, {"key": "c4", "label": "動能濾網：近 20 日報酬為正", "pass": true}, {"key": "c5a", "label": "型態：前三日收盤連續遞減", "pass": false}, {"key": "c5b", "label": "型態：第2、3日收黑（2 黑）", "pass": false}, {"key": "c5c", "label": "型態：第4日翻紅突破（1 紅）", "pass": false}]}, "kline": [{"time": "2026-05-08", "open": 40.09, "high": 40.05, "low": 37.55, "close": 38.65, "volume": 1084}, {"time": "2026-05-11", "open": 38.45, "high": 41.55, "low": 38.35, "close": 39.6, "volume": 1121}, {"time": "2026-05-12", "open": 39.89, "high": 40.9, "low": 38.75, "close": 39.05, "volume": 819}, {"time": "2026-05-13", "open": 39.37, "high": 41.0, "low": 38.05, "close": 38.85, "volume": 802}, {"time": "2026-05-14", "open": 39.37, "high": 39.5, "low": 36.6, "close": 36.85, "volume": 1203}, {"time": "2026-05-15", "open": 37.54, "high": 37.5, "low": 33.1, "close": 33.45, "volume": 1978}, {"time": "2026-05-18", "open": 34.94, "high": 34.15, "low": 31.4, "close": 34.15, "volume": 630}, {"time": "2026-05-19", "open": 32.74, "high": 35.5, "low": 33.8, "close": 34.15, "volume": 436}, {"time": "2026-05-20", "open": 34.52, "high": 34.65, "low": 33.0, "close": 33.45, "volume": 299}, {"time": "2026-05-21", "open": 33.8, "high": 35.7, "low": 33.45, "close": 35.45, "volume": 413}, {"time": "2026-05-22", "open": 35.06, "high": 36.45, "low": 34.0, "close": 34.9, "volume": 360}, {"time": "2026-05-25", "open": 35.27, "high": 35.75, "low": 34.15, "close": 34.6, "volume": 713}, {"time": "2026-05-26", "open": 34.56, "high": 35.0, "low": 33.65, "close": 34.1, "volume": 545}, {"time": "2026-05-27", "open": 34.01, "high": 34.15, "low": 32.6, "close": 32.65, "volume": 818}, {"time": "2026-05-28", "open": 33.27, "high": 33.35, "low": 30.1, "close": 30.15, "volume": 1069}, {"time": "2026-05-29", "open": 32.3, "high": 32.25, "low": 30.0, "close": 32.0, "volume": 820}, {"time": "2026-06-01", "open": 31.66, "high": 35.15, "low": 32.0, "close": 34.85, "volume": 923}, {"time": "2026-06-02", "open": 34.34, "high": 35.25, "low": 33.35, "close": 33.6, "volume": 565}, {"time": "2026-06-03", "open": 34.37, "high": 34.55, "low": 33.05, "close": 33.65, "volume": 269}, {"time": "2026-06-04", "open": 33.65, "high": 33.9, "low": 32.9, "close": 33.05, "volume": 458}, {"time": "2026-06-05", "open": 33.43, "high": 33.95, "low": 32.8, "close": 33.3, "volume": 202}, {"time": "2026-06-08", "open": 33.33, "high": 31.65, "low": 29.95, "close": 30.55, "volume": 846}, {"time": "2026-06-09", "open": 30.55, "high": 34.0, "low": 30.5, "close": 32.45, "volume": 472}, {"time": "2026-06-10", "open": 32.05, "high": 32.5, "low": 29.55, "close": 30.7, "volume": 676}, {"time": "2026-06-11", "open": 31.01, "high": 31.45, "low": 29.7, "close": 30.9, "volume": 577}, {"time": "2026-06-12", "open": 30.25, "high": 34.75, "low": 30.9, "close": 33.9, "volume": 1409}, {"time": "2026-06-15", "open": 33.46, "high": 35.55, "low": 33.3, "close": 33.8, "volume": 1030}, {"time": "2026-06-16", "open": 34.11, "high": 34.7, "low": 32.7, "close": 33.5, "volume": 796}, {"time": "2026-06-17", "open": 33.43, "high": 35.0, "low": 32.85, "close": 34.65, "volume": 803}, {"time": "2026-06-18", "open": 33.93, "high": 35.75, "low": 33.9, "close": 34.5, "volume": 586}, {"time": "2026-06-22", "open": 34.53, "high": 35.65, "low": 33.4, "close": 33.9, "volume": 585}, {"time": "2026-06-23", "open": 34.44, "high": 34.15, "low": 31.9, "close": 32.5, "volume": 593}, {"time": "2026-06-24", "open": 32.79, "high": 34.85, "low": 31.1, "close": 34.15, "volume": 901}, {"time": "2026-06-25", "open": 34.24, "high": 39.2, "low": 34.5, "close": 36.45, "volume": 2308}, {"time": "2026-06-26", "open": 37.1, "high": 37.0, "low": 33.05, "close": 33.65, "volume": 1569}], "instBars": [{"time": "2026-05-08", "value": 0}, {"time": "2026-05-11", "value": -43}, {"time": "2026-05-12", "value": 36}, {"time": "2026-05-13", "value": -11}, {"time": "2026-05-14", "value": -28}, {"time": "2026-05-21", "value": 16}, {"time": "2026-05-22", "value": -10}, {"time": "2026-05-25", "value": -1}, {"time": "2026-05-26", "value": -5}, {"time": "2026-05-29", "value": 2}, {"time": "2026-06-01", "value": 14}, {"time": "2026-06-02", "value": -13}, {"time": "2026-06-03", "value": -3}, {"time": "2026-06-08", "value": 23}, {"time": "2026-06-09", "value": -16}, {"time": "2026-06-10", "value": 20}, {"time": "2026-06-11", "value": -9}, {"time": "2026-06-12", "value": 105}, {"time": "2026-06-15", "value": -71}, {"time": "2026-06-16", "value": -14}, {"time": "2026-06-17", "value": 43}, {"time": "2026-06-18", "value": -4}, {"time": "2026-06-22", "value": -37}, {"time": "2026-06-24", "value": -2}, {"time": "2026-06-25", "value": 109}, {"time": "2026-06-26", "value": -77}], "foreignTrend": [], "sparkCloses": [34.9, 34.6, 34.1, 32.65, 30.15, 32.0, 34.85, 33.6, 33.65, 33.05, 33.3, 30.55, 32.45, 30.7, 30.9, 33.9, 33.8, 33.5, 34.65, 34.5, 33.9, 32.5, 34.15, 36.45, 33.65]}