{"id": "8935", "name": "邦泰", "price": 20.2, "change": 0.0, "changePct": 0.0, "volume": 398, "turnover": 0.08, "marketCap": 23, "shares": 1.13, "instNet": 29, "instStreak": 1, "foreignPct": 1.8, "score": 34, "roe": null, "per": 0.0, "pbr": 2.63, "yieldPct": 0.0, "rating": {"level": 1, "label": "偏空", "cls": "r-d"}, "ratingLevel": 1, "fired": false, "sig": {"fired": false, "instBacked": true, "signalIndex": 34, "conditions": [{"key": "c1", "label": "量價突破：單日漲幅 > 4%", "pass": false}, {"key": "c2", "label": "創近 15 日收盤新高", "pass": false}, {"key": "c3", "label": "帶量上攻：量 > 前5日均量 ×1.5", "pass": false}, {"key": "c4", "label": "動能濾網：近 20 日報酬為正", "pass": true}, {"key": "c5a", "label": "型態：前三日收盤連續遞減", "pass": false}, {"key": "c5b", "label": "型態：第2、3日收黑（2 黑）", "pass": false}, {"key": "c5c", "label": "型態：第4日翻紅突破（1 紅）", "pass": true}]}, "kline": [{"time": "2026-05-08", "open": 18.9, "high": 18.9, "low": 18.25, "close": 18.5, "volume": 259}, {"time": "2026-05-11", "open": 18.45, "high": 18.45, "low": 18.0, "close": 18.1, "volume": 588}, {"time": "2026-05-12", "open": 18.2, "high": 19.2, "low": 18.2, "close": 18.8, "volume": 559}, {"time": "2026-05-13", "open": 18.8, "high": 19.2, "low": 18.7, "close": 19.15, "volume": 664}, {"time": "2026-05-14", "open": 19.3, "high": 19.65, "low": 19.0, "close": 19.05, "volume": 481}, {"time": "2026-05-15", "open": 19.15, "high": 20.95, "low": 19.15, "close": 19.8, "volume": 2365}, {"time": "2026-05-18", "open": 19.8, "high": 20.65, "low": 19.35, "close": 20.05, "volume": 1525}, {"time": "2026-05-19", "open": 20.05, "high": 20.3, "low": 19.5, "close": 20.05, "volume": 594}, {"time": "2026-05-20", "open": 20.15, "high": 20.15, "low": 19.6, "close": 19.65, "volume": 364}, {"time": "2026-05-21", "open": 20.6, "high": 20.65, "low": 20.0, "close": 20.25, "volume": 429}, {"time": "2026-05-22", "open": 20.4, "high": 20.4, "low": 20.0, "close": 20.0, "volume": 542}, {"time": "2026-05-25", "open": 20.35, "high": 20.6, "low": 19.9, "close": 20.2, "volume": 770}, {"time": "2026-05-26", "open": 20.3, "high": 20.4, "low": 19.9, "close": 19.95, "volume": 627}, {"time": "2026-05-27", "open": 19.95, "high": 20.1, "low": 19.65, "close": 19.8, "volume": 515}, {"time": "2026-05-28", "open": 19.75, "high": 20.4, "low": 19.75, "close": 19.85, "volume": 701}, {"time": "2026-05-29", "open": 20.2, "high": 21.25, "low": 20.1, "close": 21.0, "volume": 930}, {"time": "2026-06-01", "open": 21.3, "high": 21.3, "low": 20.45, "close": 20.85, "volume": 912}, {"time": "2026-06-02", "open": 20.85, "high": 22.85, "low": 20.85, "close": 22.25, "volume": 1577}, {"time": "2026-06-03", "open": 21.95, "high": 22.9, "low": 21.8, "close": 22.7, "volume": 1446}, {"time": "2026-06-04", "open": 22.55, "high": 23.45, "low": 22.2, "close": 23.05, "volume": 991}, {"time": "2026-06-05", "open": 23.45, "high": 24.85, "low": 22.05, "close": 23.75, "volume": 3113}, {"time": "2026-06-08", "open": 22.3, "high": 24.35, "low": 22.15, "close": 23.8, "volume": 1630}, {"time": "2026-06-09", "open": 24.1, "high": 24.1, "low": 22.3, "close": 23.0, "volume": 1583}, {"time": "2026-06-10", "open": 22.6, "high": 23.4, "low": 21.5, "close": 21.5, "volume": 1010}, {"time": "2026-06-11", "open": 21.5, "high": 21.75, "low": 20.7, "close": 21.2, "volume": 662}, {"time": "2026-06-12", "open": 21.3, "high": 22.05, "low": 21.1, "close": 21.9, "volume": 434}, {"time": "2026-06-15", "open": 21.9, "high": 22.75, "low": 21.8, "close": 22.1, "volume": 610}, {"time": "2026-06-16", "open": 22.45, "high": 23.5, "low": 22.1, "close": 22.15, "volume": 734}, {"time": "2026-06-17", "open": 22.2, "high": 22.45, "low": 21.9, "close": 22.05, "volume": 396}, {"time": "2026-06-18", "open": 22.35, "high": 23.25, "low": 22.35, "close": 22.75, "volume": 848}, {"time": "2026-06-22", "open": 23.1, "high": 23.35, "low": 22.05, "close": 22.35, "volume": 756}, {"time": "2026-06-23", "open": 22.65, "high": 22.65, "low": 20.55, "close": 20.7, "volume": 872}, {"time": "2026-06-24", "open": 20.7, "high": 21.5, "low": 20.25, "close": 20.95, "volume": 318}, {"time": "2026-06-25", "open": 21.0, "high": 21.0, "low": 20.15, "close": 20.2, "volume": 307}, {"time": "2026-06-26", "open": 20.05, "high": 20.4, "low": 19.95, "close": 20.2, "volume": 398}], "instBars": [{"time": "2026-05-15", "value": 338}, {"time": "2026-05-18", "value": 29}, {"time": "2026-05-19", "value": -11}, {"time": "2026-05-20", "value": 22}, {"time": "2026-05-21", "value": 112}, {"time": "2026-05-22", "value": 48}, {"time": "2026-05-25", "value": 283}, {"time": "2026-05-26", "value": -130}, {"time": "2026-05-27", "value": 63}, {"time": "2026-05-28", "value": 217}, {"time": "2026-05-29", "value": 323}, {"time": "2026-06-01", "value": -384}, {"time": "2026-06-02", "value": 292}, {"time": "2026-06-03", "value": 158}, {"time": "2026-06-04", "value": 119}, {"time": "2026-06-05", "value": -540}, {"time": "2026-06-08", "value": -59}, {"time": "2026-06-09", "value": -469}, {"time": "2026-06-10", "value": 217}, {"time": "2026-06-11", "value": 87}, {"time": "2026-06-12", "value": -90}, {"time": "2026-06-15", "value": 154}, {"time": "2026-06-16", "value": 5}, {"time": "2026-06-17", "value": -6}, {"time": "2026-06-18", "value": 197}, {"time": "2026-06-22", "value": -103}, {"time": "2026-06-23", "value": -319}, {"time": "2026-06-24", "value": -29}, {"time": "2026-06-25", "value": -104}, {"time": "2026-06-26", "value": 29}], "foreignTrend": [{"time": "2026-05-14", "value": 1.43}, {"time": "2026-05-15", "value": 1.72}, {"time": "2026-05-18", "value": 1.75}, {"time": "2026-05-19", "value": 1.74}, {"time": "2026-05-20", "value": 1.76}, {"time": "2026-05-21", "value": 1.86}, {"time": "2026-05-22", "value": 1.9}, {"time": "2026-05-25", "value": 2.15}, {"time": "2026-05-26", "value": 2.03}, {"time": "2026-05-27", "value": 2.09}, {"time": "2026-05-28", "value": 2.28}, {"time": "2026-05-29", "value": 2.57}, {"time": "2026-06-01", "value": 2.23}, {"time": "2026-06-02", "value": 2.48}, {"time": "2026-06-03", "value": 2.62}, {"time": "2026-06-04", "value": 2.73}, {"time": "2026-06-05", "value": 2.25}, {"time": "2026-06-08", "value": 2.2}, {"time": "2026-06-09", "value": 1.79}, {"time": "2026-06-10", "value": 1.98}, {"time": "2026-06-11", "value": 2.06}, {"time": "2026-06-12", "value": 1.98}, {"time": "2026-06-15", "value": 2.11}, {"time": "2026-06-16", "value": 2.12}, {"time": "2026-06-17", "value": 2.11}, {"time": "2026-06-18", "value": 2.29}, {"time": "2026-06-22", "value": 2.19}, {"time": "2026-06-23", "value": 1.91}, {"time": "2026-06-24", "value": 1.89}, {"time": "2026-06-25", "value": 1.8}], "sparkCloses": [20.0, 20.2, 19.95, 19.8, 19.85, 21.0, 20.85, 22.25, 22.7, 23.05, 23.75, 23.8, 23.0, 21.5, 21.2, 21.9, 22.1, 22.15, 22.05, 22.75, 22.35, 20.7, 20.95, 20.2, 20.2]}