{"id": "9919", "name": "康那香", "price": 13.55, "change": -0.35, "changePct": -2.52, "volume": 747, "turnover": 0.1, "marketCap": 26, "shares": 1.95, "instNet": -410, "instStreak": 0, "foreignPct": 4.85, "score": 34, "roe": null, "per": 0.0, "pbr": 1.31, "yieldPct": 0.0, "rating": {"level": 0, "label": "強力偏空", "cls": "r-sd"}, "ratingLevel": 0, "fired": false, "sig": {"fired": false, "instBacked": false, "signalIndex": 34, "conditions": [{"key": "c1", "label": "量價突破：單日漲幅 > 4%", "pass": false}, {"key": "c2", "label": "創近 15 日收盤新高", "pass": false}, {"key": "c3", "label": "帶量上攻：量 > 前5日均量 ×1.5", "pass": false}, {"key": "c4", "label": "動能濾網：近 20 日報酬為正", "pass": false}, {"key": "c5a", "label": "型態：前三日收盤連續遞減", "pass": false}, {"key": "c5b", "label": "型態：第2、3日收黑（2 黑）", "pass": false}, {"key": "c5c", "label": "型態：第4日翻紅突破（1 紅）", "pass": false}]}, "kline": [{"time": "2026-05-08", "open": 14.55, "high": 15.1, "low": 14.55, "close": 14.55, "volume": 1769}, {"time": "2026-05-11", "open": 14.75, "high": 15.3, "low": 14.6, "close": 14.65, "volume": 976}, {"time": "2026-05-12", "open": 14.6, "high": 14.6, "low": 14.1, "close": 14.2, "volume": 1049}, {"time": "2026-05-13", "open": 14.3, "high": 14.3, "low": 14.05, "close": 14.2, "volume": 279}, {"time": "2026-05-14", "open": 14.3, "high": 14.4, "low": 14.2, "close": 14.2, "volume": 281}, {"time": "2026-05-15", "open": 14.35, "high": 14.35, "low": 14.0, "close": 14.0, "volume": 461}, {"time": "2026-05-18", "open": 14.4, "high": 14.8, "low": 14.1, "close": 14.3, "volume": 830}, {"time": "2026-05-19", "open": 14.4, "high": 14.6, "low": 14.2, "close": 14.35, "volume": 553}, {"time": "2026-05-20", "open": 14.55, "high": 14.55, "low": 14.1, "close": 14.25, "volume": 250}, {"time": "2026-05-21", "open": 14.4, "high": 14.4, "low": 14.2, "close": 14.3, "volume": 571}, {"time": "2026-05-22", "open": 14.35, "high": 14.4, "low": 14.15, "close": 14.25, "volume": 481}, {"time": "2026-05-25", "open": 14.4, "high": 14.4, "low": 14.05, "close": 14.3, "volume": 768}, {"time": "2026-05-26", "open": 14.3, "high": 14.35, "low": 14.0, "close": 14.15, "volume": 549}, {"time": "2026-05-27", "open": 14.25, "high": 14.3, "low": 14.1, "close": 14.15, "volume": 446}, {"time": "2026-05-28", "open": 14.2, "high": 14.25, "low": 14.0, "close": 14.1, "volume": 450}, {"time": "2026-05-29", "open": 14.1, "high": 14.15, "low": 14.05, "close": 14.1, "volume": 487}, {"time": "2026-06-01", "open": 14.1, "high": 14.3, "low": 14.0, "close": 14.15, "volume": 956}, {"time": "2026-06-02", "open": 14.2, "high": 14.2, "low": 13.9, "close": 14.15, "volume": 596}, {"time": "2026-06-03", "open": 14.2, "high": 14.3, "low": 14.05, "close": 14.25, "volume": 941}, {"time": "2026-06-04", "open": 14.3, "high": 14.7, "low": 14.25, "close": 14.55, "volume": 1098}, {"time": "2026-06-05", "open": 14.55, "high": 14.55, "low": 14.15, "close": 14.2, "volume": 648}, {"time": "2026-06-08", "open": 13.8, "high": 14.15, "low": 13.5, "close": 14.0, "volume": 679}, {"time": "2026-06-09", "open": 14.05, "high": 14.15, "low": 13.95, "close": 14.05, "volume": 376}, {"time": "2026-06-10", "open": 14.3, "high": 14.3, "low": 14.05, "close": 14.05, "volume": 505}, {"time": "2026-06-11", "open": 14.2, "high": 14.2, "low": 13.95, "close": 14.0, "volume": 358}, {"time": "2026-06-12", "open": 14.0, "high": 14.25, "low": 14.0, "close": 14.15, "volume": 590}, {"time": "2026-06-15", "open": 14.25, "high": 14.3, "low": 14.1, "close": 14.15, "volume": 403}, {"time": "2026-06-16", "open": 14.15, "high": 14.2, "low": 14.05, "close": 14.15, "volume": 238}, {"time": "2026-06-17", "open": 14.15, "high": 14.2, "low": 14.1, "close": 14.15, "volume": 241}, {"time": "2026-06-18", "open": 14.1, "high": 14.2, "low": 14.0, "close": 14.0, "volume": 505}, {"time": "2026-06-22", "open": 14.0, "high": 14.0, "low": 13.8, "close": 13.9, "volume": 1151}, {"time": "2026-06-23", "open": 14.05, "high": 14.05, "low": 13.85, "close": 13.9, "volume": 505}, {"time": "2026-06-24", "open": 13.85, "high": 13.9, "low": 13.75, "close": 13.9, "volume": 571}, {"time": "2026-06-25", "open": 13.9, "high": 13.9, "low": 13.8, "close": 13.9, "volume": 401}, {"time": "2026-06-26", "open": 13.85, "high": 13.85, "low": 13.55, "close": 13.55, "volume": 747}], "instBars": [{"time": "2026-05-15", "value": 7}, {"time": "2026-05-18", "value": -194}, {"time": "2026-05-19", "value": -30}, {"time": "2026-05-20", "value": -59}, {"time": "2026-05-21", "value": 300}, {"time": "2026-05-22", "value": -138}, {"time": "2026-05-25", "value": -131}, {"time": "2026-05-26", "value": -47}, {"time": "2026-05-27", "value": 88}, {"time": "2026-05-28", "value": -64}, {"time": "2026-05-29", "value": 54}, {"time": "2026-06-01", "value": 464}, {"time": "2026-06-02", "value": -24}, {"time": "2026-06-03", "value": 485}, {"time": "2026-06-04", "value": 30}, {"time": "2026-06-05", "value": -177}, {"time": "2026-06-08", "value": 220}, {"time": "2026-06-09", "value": -24}, {"time": "2026-06-10", "value": 5}, {"time": "2026-06-11", "value": -91}, {"time": "2026-06-12", "value": 311}, {"time": "2026-06-15", "value": 237}, {"time": "2026-06-16", "value": -24}, {"time": "2026-06-17", "value": 2}, {"time": "2026-06-18", "value": 51}, {"time": "2026-06-22", "value": -14}, {"time": "2026-06-23", "value": -136}, {"time": "2026-06-24", "value": 82}, {"time": "2026-06-25", "value": -137}, {"time": "2026-06-26", "value": -410}], "foreignTrend": [{"time": "2026-05-14", "value": 4.46}, {"time": "2026-05-15", "value": 4.46}, {"time": "2026-05-18", "value": 4.36}, {"time": "2026-05-19", "value": 4.36}, {"time": "2026-05-20", "value": 4.34}, {"time": "2026-05-21", "value": 4.51}, {"time": "2026-05-22", "value": 4.44}, {"time": "2026-05-25", "value": 4.4}, {"time": "2026-05-26", "value": 4.4}, {"time": "2026-05-27", "value": 4.43}, {"time": "2026-05-28", "value": 4.41}, {"time": "2026-05-29", "value": 4.45}, {"time": "2026-06-01", "value": 4.68}, {"time": "2026-06-02", "value": 4.7}, {"time": "2026-06-03", "value": 4.96}, {"time": "2026-06-04", "value": 4.98}, {"time": "2026-06-05", "value": 4.88}, {"time": "2026-06-08", "value": 5.0}, {"time": "2026-06-09", "value": 4.99}, {"time": "2026-06-10", "value": 4.9}, {"time": "2026-06-11", "value": 4.84}, {"time": "2026-06-12", "value": 5.0}, {"time": "2026-06-15", "value": 5.12}, {"time": "2026-06-16", "value": 5.1}, {"time": "2026-06-17", "value": 5.05}, {"time": "2026-06-18", "value": 5.08}, {"time": "2026-06-22", "value": 4.98}, {"time": "2026-06-23", "value": 4.91}, {"time": "2026-06-24", "value": 4.94}, {"time": "2026-06-25", "value": 4.85}], "sparkCloses": [14.25, 14.3, 14.15, 14.15, 14.1, 14.1, 14.15, 14.15, 14.25, 14.55, 14.2, 14.0, 14.05, 14.05, 14.0, 14.15, 14.15, 14.15, 14.15, 14.0, 13.9, 13.9, 13.9, 13.9, 13.55]}